gradium/__init__.py
gradium/core.py
gradium-0.0.1.dist-info/METADATA
gradium-0.0.1.dist-info/WHEEL
gradium-0.0.1.dist-info/top_level.txt
gradium-0.0.1.dist-info/RECORD
